{
  "$type": "ThunderRoad.ItemData, ThunderRoad",
  "id": "KyberCrystalIndigoFlicker",
  "version": 4,
  "localizationId": "KyberCrystalIndigoFlicker",
  "displayName": "Kyber Crystal (Indigo - Flicker)",
  "description": "",
  "author": "Ryan H.",
  "valueType": "Gold",
  "value": 0,
  "rewardValue": 0.0,
  "tier": 0,
  "flags": "Spinnable",
  "levelRequired": 0,
  "category": "Kyber Crystals",
  "iconEffectId": null,
  "preferredItemCenter": "Mass",
  "drainImbueWhenIdle": true,
  "prefabAddress": "theouterrim_lightsabers.KyberCrystal5",
  "iconAddress": "theouterrim_lightsabers.KyberCrystalMagenta.Icon",
  "closeUpIconAddress": null,
  "pooledCount": 0,
  "androidPooledCount": 0,
  "type": "Misc",
  "allowedStorage": "Container, SandboxAllItems",
  "despawnOnStoredInInventory": false,
  "isStackable": true,
  "consumableId": null,
  "slot": "Medium",
  "snapAudioContainerAddress": null,
  "overrideMassAndDrag": true,
  "mass": 0.1,
  "drag": 1.0,
  "angularDrag": 0.05,
  "focusRegenMultiplier": 1.0,
  "spellChargeSpeedPlayerMultiplier": 1.0,
  "spellChargeSpeedNPCMultiplier": 1.0,
  "collisionMaxOverride": 0,
  "collisionEnterOnly": false,
  "collisionNoMinVelocityCheck": false,
  "forceLayer": "None",
  "diffForceLayerWhenHeld": false,
  "forceLayerHeld": "None",
  "throwMultiplier": 1.0,
  "runSpeedMultiplier": 1.0,
  "flyRotationSpeed": 2.0,
  "flyThrowAngle": 0.0,
  "allowFlyBackwards": false,
  "telekinesisSafeDistance": 1.0,
  "telekinesisThrowRatio": 1.0,
  "telekinesisAutoGrabAnyHandle": false,
  "grippable": true,
  "grabAndGripClimb": false,
  "playerGrabAndGripChangeLayer": true,
  "customSnaps": [],
  "drainImbueOnSnap": true,
  "modules": [
    {
      "$type": "TOR.ItemModuleKyberCrystal, TheOuterRim",
      "bladeColour": [0.4, 0, 1, 1],
      "glowColour": [0.3, 0, 1, 1],
      "coreColour": [1, 1, 1, 1],
      "innerGlow": 0.5,
      "coreRadius": 0.99,
      "coreStrength": 1.0,
      "flicker": 2.0,
      "isUnstable": false,
      "idleSound": "theouterrim_lightsabers.LightsaberIdlePurpleBlack",
      "idleSoundVolume": 0.6,
      "idleSoundPitch": 1.0,
      "startSound": "theouterrim_lightsabers.LightsaberStartYellow",
      "startSoundVolume": 0.6,
      "startSoundPitch": 1.0,
      "stopSound": "theouterrim_lightsabers.LightsaberStopPurpleBlack",
      "stopSoundVolume": 0.6,
      "stopSoundPitch": 1.0,
      "whooshFX": "WhooshLightsaberGreen"
    }
  ],
  "colliderGroups": [],
  "damagers": [
    {
      "transformName": "Blunt",
      "damagerID": "HandleLight"
    }
  ],
  "Interactables": [
    {
      "transformName": "Handle",
      "interactableId": "ObjectHandleLight",
      "overrideHandPose": true,
      "handPoseId": "HandleKyberCrystal"
    }
  ],
  "effectHinges": [],
  "whooshs": []
}